[
   {
      "pk" : 1,
      "model" : "auth.permission",
      "fields" : {
         "content_type" : 1,
         "name" : "Can add log entry",
         "codename" : "add_logentry"
      }
   },
   {
      "model" : "auth.permission",
      "pk" : 2,
      "fields" : {
         "content_type" : 1,
         "codename" : "change_logentry",
         "name" : "Can change log entry"
      }
   },
   {
      "pk" : 3,
      "model" : "auth.permission",
      "fields" : {
         "codename" : "delete_logentry",
         "name" : "Can delete log entry",
         "content_type" : 1
      }
   },
   {
      "fields" : {
         "content_type" : 2,
         "name" : "Can add permission",
         "codename" : "add_permission"
      },
      "model" : "auth.permission",
      "pk" : 4
   },
   {
      "pk" : 5,
      "model" : "auth.permission",
      "fields" : {
         "codename" : "change_permission",
         "name" : "Can change permission",
         "content_type" : 2
      }
   },
   {
      "fields" : {
         "content_type" : 2,
         "codename" : "delete_permission",
         "name" : "Can delete permission"
      },
      "pk" : 6,
      "model" : "auth.permission"
   },
   {
      "fields" : {
         "content_type" : 3,
         "codename" : "add_group",
         "name" : "Can add group"
      },
      "pk" : 7,
      "model" : "auth.permission"
   },
   {
      "model" : "auth.permission",
      "pk" : 8,
      "fields" : {
         "content_type" : 3,
         "codename" : "change_group",
         "name" : "Can change group"
      }
   },
   {
      "model" : "auth.permission",
      "pk" : 9,
      "fields" : {
         "content_type" : 3,
         "codename" : "delete_group",
         "name" : "Can delete group"
      }
   },
   {
      "fields" : {
         "content_type" : 4,
         "name" : "Can add user",
         "codename" : "add_user"
      },
      "pk" : 10,
      "model" : "auth.permission"
   },
   {
      "fields" : {
         "codename" : "change_user",
         "name" : "Can change user",
         "content_type" : 4
      },
      "pk" : 11,
      "model" : "auth.permission"
   },
   {
      "fields" : {
         "content_type" : 4,
         "codename" : "delete_user",
         "name" : "Can delete user"
      },
      "pk" : 12,
      "model" : "auth.permission"
   },
   {
      "fields" : {
         "codename" : "add_contenttype",
         "name" : "Can add content type",
         "content_type" : 5
      },
      "pk" : 13,
      "model" : "auth.permission"
   },
   {
      "pk" : 14,
      "model" : "auth.permission",
      "fields" : {
         "codename" : "change_contenttype",
         "name" : "Can change content type",
         "content_type" : 5
      }
   },
   {
      "fields" : {
         "content_type" : 5,
         "name" : "Can delete content type",
         "codename" : "delete_contenttype"
      },
      "model" : "auth.permission",
      "pk" : 15
   },
   {
      "pk" : 16,
      "model" : "auth.permission",
      "fields" : {
         "content_type" : 6,
         "name" : "Can add session",
         "codename" : "add_session"
      }
   },
   {
      "fields" : {
         "content_type" : 6,
         "name" : "Can change session",
         "codename" : "change_session"
      },
      "model" : "auth.permission",
      "pk" : 17
   },
   {
      "fields" : {
         "codename" : "delete_session",
         "name" : "Can delete session",
         "content_type" : 6
      },
      "pk" : 18,
      "model" : "auth.permission"
   },
   {
      "model" : "auth.permission",
      "pk" : 19,
      "fields" : {
         "content_type" : 7,
         "name" : "Can add site",
         "codename" : "add_site"
      }
   },
   {
      "pk" : 20,
      "model" : "auth.permission",
      "fields" : {
         "name" : "Can change site",
         "codename" : "change_site",
         "content_type" : 7
      }
   },
   {
      "fields" : {
         "content_type" : 7,
         "name" : "Can delete site",
         "codename" : "delete_site"
      },
      "model" : "auth.permission",
      "pk" : 21
   },
   {
      "fields" : {
         "name" : "Can add cors model",
         "codename" : "add_corsmodel",
         "content_type" : 8
      },
      "pk" : 22,
      "model" : "auth.permission"
   },
   {
      "model" : "auth.permission",
      "pk" : 23,
      "fields" : {
         "content_type" : 8,
         "name" : "Can change cors model",
         "codename" : "change_corsmodel"
      }
   },
   {
      "pk" : 24,
      "model" : "auth.permission",
      "fields" : {
         "content_type" : 8,
         "codename" : "delete_corsmodel",
         "name" : "Can delete cors model"
      }
   },
   {
      "model" : "auth.permission",
      "pk" : 25,
      "fields" : {
         "content_type" : 9,
         "name" : "Can add organisation",
         "codename" : "add_organisation"
      }
   },
   {
      "model" : "auth.permission",
      "pk" : 26,
      "fields" : {
         "name" : "Can change organisation",
         "codename" : "change_organisation",
         "content_type" : 9
      }
   },
   {
      "fields" : {
         "content_type" : 9,
         "codename" : "delete_organisation",
         "name" : "Can delete organisation"
      },
      "model" : "auth.permission",
      "pk" : 27
   },
   {
      "fields" : {
         "name" : "Can add editing role user",
         "codename" : "add_editingroleuser",
         "content_type" : 10
      },
      "model" : "auth.permission",
      "pk" : 28
   },
   {
      "fields" : {
         "content_type" : 10,
         "codename" : "change_editingroleuser",
         "name" : "Can change editing role user"
      },
      "pk" : 29,
      "model" : "auth.permission"
   },
   {
      "model" : "auth.permission",
      "pk" : 30,
      "fields" : {
         "content_type" : 10,
         "name" : "Can delete editing role user",
         "codename" : "delete_editingroleuser"
      }
   },
   {
      "pk" : 31,
      "model" : "auth.permission",
      "fields" : {
         "name" : "Can add editing role group",
         "codename" : "add_editingrolegroup",
         "content_type" : 11
      }
   },
   {
      "model" : "auth.permission",
      "pk" : 32,
      "fields" : {
         "codename" : "change_editingrolegroup",
         "name" : "Can change editing role group",
         "content_type" : 11
      }
   },
   {
      "pk" : 33,
      "model" : "auth.permission",
      "fields" : {
         "content_type" : 11,
         "name" : "Can delete editing role group",
         "codename" : "delete_editingrolegroup"
      }
   },
   {
      "pk" : 34,
      "model" : "auth.permission",
      "fields" : {
         "name" : "Can add bioproject",
         "codename" : "add_bioproject",
         "content_type" : 12
      }
   },
   {
      "fields" : {
         "content_type" : 12,
         "name" : "Can change bioproject",
         "codename" : "change_bioproject"
      },
      "model" : "auth.permission",
      "pk" : 35
   },
   {
      "model" : "auth.permission",
      "pk" : 36,
      "fields" : {
         "name" : "Can delete bioproject",
         "codename" : "delete_bioproject",
         "content_type" : 12
      }
   },
   {
      "fields" : {
         "codename" : "add_emailconfirmation",
         "name" : "Can add email confirmation",
         "content_type" : 13
      },
      "pk" : 37,
      "model" : "auth.permission"
   },
   {
      "pk" : 38,
      "model" : "auth.permission",
      "fields" : {
         "content_type" : 13,
         "codename" : "change_emailconfirmation",
         "name" : "Can change email confirmation"
      }
   },
   {
      "model" : "auth.permission",
      "pk" : 39,
      "fields" : {
         "codename" : "delete_emailconfirmation",
         "name" : "Can delete email confirmation",
         "content_type" : 13
      }
   },
   {
      "fields" : {
         "name" : "Can add account deletion",
         "codename" : "add_accountdeletion",
         "content_type" : 14
      },
      "pk" : 40,
      "model" : "auth.permission"
   },
   {
      "fields" : {
         "codename" : "change_accountdeletion",
         "name" : "Can change account deletion",
         "content_type" : 14
      },
      "model" : "auth.permission",
      "pk" : 41
   },
   {
      "pk" : 42,
      "model" : "auth.permission",
      "fields" : {
         "content_type" : 14,
         "name" : "Can delete account deletion",
         "codename" : "delete_accountdeletion"
      }
   },
   {
      "fields" : {
         "codename" : "add_signupcoderesult",
         "name" : "Can add signup code result",
         "content_type" : 15
      },
      "pk" : 43,
      "model" : "auth.permission"
   },
   {
      "fields" : {
         "content_type" : 15,
         "name" : "Can change signup code result",
         "codename" : "change_signupcoderesult"
      },
      "pk" : 44,
      "model" : "auth.permission"
   },
   {
      "fields" : {
         "content_type" : 15,
         "name" : "Can delete signup code result",
         "codename" : "delete_signupcoderesult"
      },
      "pk" : 45,
      "model" : "auth.permission"
   },
   {
      "model" : "auth.permission",
      "pk" : 46,
      "fields" : {
         "content_type" : 16,
         "codename" : "add_emailaddress",
         "name" : "Can add email address"
      }
   },
   {
      "fields" : {
         "codename" : "change_emailaddress",
         "name" : "Can change email address",
         "content_type" : 16
      },
      "model" : "auth.permission",
      "pk" : 47
   },
   {
      "pk" : 48,
      "model" : "auth.permission",
      "fields" : {
         "name" : "Can delete email address",
         "codename" : "delete_emailaddress",
         "content_type" : 16
      }
   },
   {
      "fields" : {
         "content_type" : 17,
         "codename" : "add_signupcode",
         "name" : "Can add signup code"
      },
      "pk" : 49,
      "model" : "auth.permission"
   },
   {
      "model" : "auth.permission",
      "pk" : 50,
      "fields" : {
         "content_type" : 17,
         "name" : "Can change signup code",
         "codename" : "change_signupcode"
      }
   },
   {
      "fields" : {
         "codename" : "delete_signupcode",
         "name" : "Can delete signup code",
         "content_type" : 17
      },
      "pk" : 51,
      "model" : "auth.permission"
   },
   {
      "fields" : {
         "content_type" : 18,
         "codename" : "add_account",
         "name" : "Can add account"
      },
      "model" : "auth.permission",
      "pk" : 52
   },
   {
      "fields" : {
         "name" : "Can change account",
         "codename" : "change_account",
         "content_type" : 18
      },
      "pk" : 53,
      "model" : "auth.permission"
   },
   {
      "pk" : 54,
      "model" : "auth.permission",
      "fields" : {
         "codename" : "delete_account",
         "name" : "Can delete account",
         "content_type" : 18
      }
   },
   {
      "fields" : {
         "name" : "Can add box",
         "codename" : "add_box",
         "content_type" : 19
      },
      "model" : "auth.permission",
      "pk" : 55
   },
   {
      "fields" : {
         "codename" : "change_box",
         "name" : "Can change box",
         "content_type" : 19
      },
      "pk" : 56,
      "model" : "auth.permission"
   },
   {
      "model" : "auth.permission",
      "pk" : 57,
      "fields" : {
         "name" : "Can delete box",
         "codename" : "delete_box",
         "content_type" : 19
      }
   },
   {
      "fields" : {
         "content_type" : 20,
         "name" : "Can add storage location",
         "codename" : "add_storagelocation"
      },
      "pk" : 58,
      "model" : "auth.permission"
   },
   {
      "fields" : {
         "name" : "Can change storage location",
         "codename" : "change_storagelocation",
         "content_type" : 20
      },
      "pk" : 59,
      "model" : "auth.permission"
   },
   {
      "fields" : {
         "codename" : "delete_storagelocation",
         "name" : "Can delete storage location",
         "content_type" : 20
      },
      "pk" : 60,
      "model" : "auth.permission"
   },
   {
      "fields" : {
         "content_type" : 21,
         "codename" : "add_sequencingrunpoolitem",
         "name" : "Can add sequencing run pool item"
      },
      "pk" : 61,
      "model" : "auth.permission"
   },
   {
      "pk" : 62,
      "model" : "auth.permission",
      "fields" : {
         "content_type" : 21,
         "name" : "Can change sequencing run pool item",
         "codename" : "change_sequencingrunpoolitem"
      }
   },
   {
      "fields" : {
         "content_type" : 21,
         "codename" : "delete_sequencingrunpoolitem",
         "name" : "Can delete sequencing run pool item"
      },
      "pk" : 63,
      "model" : "auth.permission"
   },
   {
      "fields" : {
         "content_type" : 22,
         "name" : "Can add bacteria",
         "codename" : "add_bacteria"
      },
      "pk" : 64,
      "model" : "auth.permission"
   },
   {
      "pk" : 65,
      "model" : "auth.permission",
      "fields" : {
         "name" : "Can change bacteria",
         "codename" : "change_bacteria",
         "content_type" : 22
      }
   },
   {
      "fields" : {
         "name" : "Can delete bacteria",
         "codename" : "delete_bacteria",
         "content_type" : 22
      },
      "model" : "auth.permission",
      "pk" : 66
   },
   {
      "pk" : 67,
      "model" : "auth.permission",
      "fields" : {
         "content_type" : 23,
         "codename" : "add_experiment",
         "name" : "Can add experiment"
      }
   },
   {
      "model" : "auth.permission",
      "pk" : 68,
      "fields" : {
         "codename" : "change_experiment",
         "name" : "Can change experiment",
         "content_type" : 23
      }
   },
   {
      "pk" : 69,
      "model" : "auth.permission",
      "fields" : {
         "codename" : "delete_experiment",
         "name" : "Can delete experiment",
         "content_type" : 23
      }
   },
   {
      "model" : "auth.permission",
      "pk" : 70,
      "fields" : {
         "content_type" : 24,
         "name" : "Can add environmental sample",
         "codename" : "add_environmentalsample"
      }
   },
   {
      "pk" : 71,
      "model" : "auth.permission",
      "fields" : {
         "codename" : "change_environmentalsample",
         "name" : "Can change environmental sample",
         "content_type" : 24
      }
   },
   {
      "model" : "auth.permission",
      "pk" : 72,
      "fields" : {
         "name" : "Can delete environmental sample",
         "codename" : "delete_environmentalsample",
         "content_type" : 24
      }
   },
   {
      "model" : "auth.permission",
      "pk" : 73,
      "fields" : {
         "content_type" : 25,
         "name" : "Can add sample type",
         "codename" : "add_sampletype"
      }
   },
   {
      "model" : "auth.permission",
      "pk" : 74,
      "fields" : {
         "content_type" : 25,
         "codename" : "change_sampletype",
         "name" : "Can change sample type"
      }
   },
   {
      "pk" : 75,
      "model" : "auth.permission",
      "fields" : {
         "codename" : "delete_sampletype",
         "name" : "Can delete sample type",
         "content_type" : 25
      }
   },
   {
      "fields" : {
         "content_type" : 26,
         "name" : "Can add experimental result",
         "codename" : "add_experimentalresult"
      },
      "pk" : 76,
      "model" : "auth.permission"
   },
   {
      "model" : "auth.permission",
      "pk" : 77,
      "fields" : {
         "content_type" : 26,
         "name" : "Can change experimental result",
         "codename" : "change_experimentalresult"
      }
   },
   {
      "fields" : {
         "codename" : "delete_experimentalresult",
         "name" : "Can delete experimental result",
         "content_type" : 26
      },
      "pk" : 78,
      "model" : "auth.permission"
   },
   {
      "fields" : {
         "content_type" : 27,
         "name" : "Can add phage",
         "codename" : "add_phage"
      },
      "pk" : 79,
      "model" : "auth.permission"
   },
   {
      "model" : "auth.permission",
      "pk" : 80,
      "fields" : {
         "content_type" : 27,
         "name" : "Can change phage",
         "codename" : "change_phage"
      }
   },
   {
      "pk" : 81,
      "model" : "auth.permission",
      "fields" : {
         "content_type" : 27,
         "name" : "Can delete phage",
         "codename" : "delete_phage"
      }
   },
   {
      "fields" : {
         "content_type" : 28,
         "name" : "Can add sequencing run",
         "codename" : "add_sequencingrun"
      },
      "model" : "auth.permission",
      "pk" : 82
   },
   {
      "pk" : 83,
      "model" : "auth.permission",
      "fields" : {
         "codename" : "change_sequencingrun",
         "name" : "Can change sequencing run",
         "content_type" : 28
      }
   },
   {
      "pk" : 84,
      "model" : "auth.permission",
      "fields" : {
         "content_type" : 28,
         "name" : "Can delete sequencing run",
         "codename" : "delete_sequencingrun"
      }
   },
   {
      "model" : "auth.permission",
      "pk" : 85,
      "fields" : {
         "name" : "Can add assembly",
         "codename" : "add_assembly",
         "content_type" : 29
      }
   },
   {
      "fields" : {
         "content_type" : 29,
         "codename" : "change_assembly",
         "name" : "Can change assembly"
      },
      "pk" : 86,
      "model" : "auth.permission"
   },
   {
      "pk" : 87,
      "model" : "auth.permission",
      "fields" : {
         "content_type" : 29,
         "codename" : "delete_assembly",
         "name" : "Can delete assembly"
      }
   },
   {
      "fields" : {
         "content_type" : 30,
         "name" : "Can add tube type",
         "codename" : "add_tubetype"
      },
      "pk" : 88,
      "model" : "auth.permission"
   },
   {
      "fields" : {
         "name" : "Can change tube type",
         "codename" : "change_tubetype",
         "content_type" : 30
      },
      "pk" : 89,
      "model" : "auth.permission"
   },
   {
      "model" : "auth.permission",
      "pk" : 90,
      "fields" : {
         "content_type" : 30,
         "codename" : "delete_tubetype",
         "name" : "Can delete tube type"
      }
   },
   {
      "fields" : {
         "codename" : "add_lysate",
         "name" : "Can add lysate",
         "content_type" : 31
      },
      "pk" : 91,
      "model" : "auth.permission"
   },
   {
      "fields" : {
         "content_type" : 31,
         "name" : "Can change lysate",
         "codename" : "change_lysate"
      },
      "model" : "auth.permission",
      "pk" : 92
   },
   {
      "fields" : {
         "codename" : "delete_lysate",
         "name" : "Can delete lysate",
         "content_type" : 31
      },
      "pk" : 93,
      "model" : "auth.permission"
   },
   {
      "fields" : {
         "content_type" : 32,
         "codename" : "add_sequencingrunpool",
         "name" : "Can add sequencing run pool"
      },
      "pk" : 94,
      "model" : "auth.permission"
   },
   {
      "fields" : {
         "codename" : "change_sequencingrunpool",
         "name" : "Can change sequencing run pool",
         "content_type" : 32
      },
      "pk" : 95,
      "model" : "auth.permission"
   },
   {
      "fields" : {
         "name" : "Can delete sequencing run pool",
         "codename" : "delete_sequencingrunpool",
         "content_type" : 32
      },
      "pk" : 96,
      "model" : "auth.permission"
   },
   {
      "fields" : {
         "content_type" : 33,
         "name" : "Can add tube",
         "codename" : "add_tube"
      },
      "pk" : 97,
      "model" : "auth.permission"
   },
   {
      "fields" : {
         "content_type" : 33,
         "codename" : "change_tube",
         "name" : "Can change tube"
      },
      "pk" : 98,
      "model" : "auth.permission"
   },
   {
      "fields" : {
         "name" : "Can delete tube",
         "codename" : "delete_tube",
         "content_type" : 33
      },
      "model" : "auth.permission",
      "pk" : 99
   },
   {
      "model" : "auth.permission",
      "pk" : 100,
      "fields" : {
         "content_type" : 34,
         "name" : "Can add phage dna prep",
         "codename" : "add_phagednaprep"
      }
   },
   {
      "model" : "auth.permission",
      "pk" : 101,
      "fields" : {
         "content_type" : 34,
         "codename" : "change_phagednaprep",
         "name" : "Can change phage dna prep"
      }
   },
   {
      "model" : "auth.permission",
      "pk" : 102,
      "fields" : {
         "content_type" : 34,
         "name" : "Can delete phage dna prep",
         "codename" : "delete_phagednaprep"
      }
   },
   {
      "pk" : 103,
      "model" : "auth.permission",
      "fields" : {
         "content_type" : 35,
         "name" : "Can add container type",
         "codename" : "add_containertype"
      }
   },
   {
      "fields" : {
         "name" : "Can change container type",
         "codename" : "change_containertype",
         "content_type" : 35
      },
      "pk" : 104,
      "model" : "auth.permission"
   },
   {
      "pk" : 105,
      "model" : "auth.permission",
      "fields" : {
         "content_type" : 35,
         "name" : "Can delete container type",
         "codename" : "delete_containertype"
      }
   },
   {
      "fields" : {
         "permissions" : [],
         "name" : "bich464-2016-admin"
      },
      "model" : "auth.group",
      "pk" : 1
   },
   {
      "model" : "auth.group",
      "pk" : 2,
      "fields" : {
         "name" : "bich464-2016-students",
         "permissions" : []
      }
   },
   {
      "pk" : 3,
      "model" : "auth.group",
      "fields" : {
         "name" : "public",
         "permissions" : []
      }
   },
   {
      "fields" : {
         "username" : "hxr",
         "is_staff" : true,
         "last_login" : "2016-10-25T20:53:52.478Z",
         "first_name" : "",
         "is_active" : true,
         "last_name" : "",
         "email" : "esr@tamu.edu",
         "groups" : [],
         "date_joined" : "2016-10-25T20:08:42.601Z",
         "password" : "pbkdf2_sha256$30000$Qd4UbUgwylq6$InZRMlR8HnqVa+tUzPwrSJJ6RlONZIg6EkcJmHXZjh0=",
         "user_permissions" : [],
         "is_superuser" : true
      },
      "pk" : 1,
      "model" : "auth.user"
   },
   {
      "model" : "auth.user",
      "pk" : 2,
      "fields" : {
         "last_login" : null,
         "is_staff" : false,
         "username" : "kkissel",
         "is_active" : true,
         "first_name" : "",
         "groups" : [],
         "last_name" : "",
         "email" : "ldvf8@gmail.com",
         "is_superuser" : false,
         "user_permissions" : [],
         "password" : "",
         "date_joined" : "2016-10-25T20:12:27.323Z"
      }
   },
   {
      "fields" : {
         "is_active" : true,
         "first_name" : "",
         "last_login" : null,
         "is_staff" : false,
         "username" : "jrediger",
         "is_superuser" : false,
         "user_permissions" : [],
         "date_joined" : "2016-10-25T20:12:27.337Z",
         "password" : "",
         "groups" : [],
         "email" : "lif0s@gmail.com",
         "last_name" : ""
      },
      "pk" : 3,
      "model" : "auth.user"
   },
   {
      "fields" : {
         "last_login" : null,
         "is_staff" : false,
         "username" : "dcade",
         "is_active" : true,
         "first_name" : "",
         "groups" : [],
         "email" : "dsww2@gmail.com",
         "last_name" : "",
         "is_superuser" : false,
         "user_permissions" : [],
         "date_joined" : "2016-10-25T20:12:27.346Z",
         "password" : ""
      },
      "pk" : 4,
      "model" : "auth.user"
   },
   {
      "pk" : 5,
      "model" : "auth.user",
      "fields" : {
         "is_superuser" : false,
         "user_permissions" : [],
         "date_joined" : "2016-10-25T20:12:27.358Z",
         "password" : "",
         "groups" : [],
         "email" : "712pf@gmail.com",
         "last_name" : "",
         "is_active" : true,
         "first_name" : "",
         "last_login" : null,
         "is_staff" : false,
         "username" : "iross"
      }
   },
   {
      "fields" : {
         "user_permissions" : [],
         "password" : "",
         "date_joined" : "2016-10-25T20:12:27.371Z",
         "is_superuser" : false,
         "groups" : [],
         "last_name" : "",
         "email" : "sw636@gmail.com",
         "is_active" : true,
         "first_name" : "",
         "username" : "kwilliamson",
         "last_login" : null,
         "is_staff" : false
      },
      "pk" : 6,
      "model" : "auth.user"
   },
   {
      "fields" : {
         "username" : "wnavarro",
         "is_staff" : false,
         "last_login" : null,
         "first_name" : "",
         "is_active" : true,
         "last_name" : "",
         "email" : "l55i6@gmail.com",
         "groups" : [],
         "password" : "",
         "date_joined" : "2016-10-25T20:12:27.382Z",
         "user_permissions" : [],
         "is_superuser" : false
      },
      "pk" : 7,
      "model" : "auth.user"
   },
   {
      "fields" : {
         "is_superuser" : false,
         "user_permissions" : [],
         "password" : "",
         "date_joined" : "2016-10-25T20:12:27.392Z",
         "groups" : [],
         "last_name" : "",
         "email" : "uwpfw@gmail.com",
         "is_active" : true,
         "first_name" : "",
         "last_login" : null,
         "is_staff" : false,
         "username" : "eleclair"
      },
      "model" : "auth.user",
      "pk" : 8
   },
   {
      "fields" : {
         "is_staff" : false,
         "last_login" : null,
         "username" : "lfigueroa",
         "first_name" : "",
         "is_active" : true,
         "last_name" : "",
         "email" : "89yhj@gmail.com",
         "groups" : [],
         "is_superuser" : false,
         "date_joined" : "2016-10-25T20:12:27.402Z",
         "password" : "",
         "user_permissions" : []
      },
      "model" : "auth.user",
      "pk" : 9
   },
   {
      "pk" : 10,
      "model" : "auth.user",
      "fields" : {
         "last_login" : null,
         "is_staff" : false,
         "username" : "lwerkhoven",
         "is_active" : true,
         "first_name" : "",
         "groups" : [],
         "last_name" : "",
         "email" : "hihv8@gmail.com",
         "is_superuser" : false,
         "user_permissions" : [],
         "date_joined" : "2016-10-25T20:12:27.412Z",
         "password" : ""
      }
   },
   {
      "model" : "auth.user",
      "pk" : 11,
      "fields" : {
         "is_active" : true,
         "first_name" : "",
         "last_login" : null,
         "is_staff" : false,
         "username" : "cryder",
         "is_superuser" : false,
         "user_permissions" : [],
         "date_joined" : "2016-10-25T20:12:27.423Z",
         "password" : "",
         "groups" : [],
         "last_name" : "",
         "email" : "kzmzh@gmail.com"
      }
   },
   {
      "fields" : {
         "groups" : [],
         "email" : "lhbto@gmail.com",
         "last_name" : "",
         "user_permissions" : [],
         "date_joined" : "2016-10-25T20:12:27.434Z",
         "password" : "",
         "is_superuser" : false,
         "username" : "dbeltron",
         "last_login" : null,
         "is_staff" : false,
         "is_active" : true,
         "first_name" : ""
      },
      "pk" : 12,
      "model" : "auth.user"
   },
   {
      "fields" : {
         "is_active" : true,
         "first_name" : "",
         "username" : "cjones",
         "last_login" : null,
         "is_staff" : false,
         "user_permissions" : [],
         "password" : "",
         "date_joined" : "2016-10-25T20:12:27.443Z",
         "is_superuser" : false,
         "groups" : [],
         "email" : "g84eg@gmail.com",
         "last_name" : ""
      },
      "pk" : 13,
      "model" : "auth.user"
   },
   {
      "fields" : {
         "first_name" : "",
         "is_active" : true,
         "is_staff" : false,
         "last_login" : null,
         "username" : "apiccolomini",
         "is_superuser" : false,
         "date_joined" : "2016-10-25T20:12:27.453Z",
         "password" : "",
         "user_permissions" : [],
         "last_name" : "",
         "email" : "0b0jr@gmail.com",
         "groups" : []
      },
      "pk" : 14,
      "model" : "auth.user"
   },
   {
      "fields" : {
         "last_login" : null,
         "is_staff" : false,
         "username" : "agildea",
         "is_active" : true,
         "first_name" : "",
         "groups" : [],
         "last_name" : "",
         "email" : "gh70h@gmail.com",
         "is_superuser" : false,
         "user_permissions" : [],
         "password" : "",
         "date_joined" : "2016-10-25T20:12:27.463Z"
      },
      "model" : "auth.user",
      "pk" : 15
   },
   {
      "pk" : 16,
      "model" : "auth.user",
      "fields" : {
         "username" : "vnicholas",
         "is_staff" : false,
         "last_login" : null,
         "first_name" : "",
         "is_active" : true,
         "last_name" : "",
         "email" : "scqwj@gmail.com",
         "groups" : [],
         "date_joined" : "2016-10-25T20:12:27.473Z",
         "password" : "",
         "user_permissions" : [],
         "is_superuser" : false
      }
   },
   {
      "model" : "auth.user",
      "pk" : 17,
      "fields" : {
         "email" : "jf6j4@gmail.com",
         "last_name" : "",
         "groups" : [],
         "password" : "",
         "date_joined" : "2016-10-25T20:12:27.484Z",
         "user_permissions" : [],
         "is_superuser" : false,
         "username" : "mpowell",
         "is_staff" : false,
         "last_login" : null,
         "first_name" : "",
         "is_active" : true
      }
   },
   {
      "fields" : {
         "username" : "jhilderbrandt",
         "last_login" : null,
         "is_staff" : false,
         "is_active" : true,
         "first_name" : "",
         "groups" : [],
         "email" : "j1fg8@gmail.com",
         "last_name" : "",
         "user_permissions" : [],
         "password" : "",
         "date_joined" : "2016-10-25T20:12:27.494Z",
         "is_superuser" : false
      },
      "model" : "auth.user",
      "pk" : 18
   },
   {
      "model" : "auth.user",
      "pk" : 19,
      "fields" : {
         "username" : "dcarmant",
         "last_login" : null,
         "is_staff" : false,
         "is_active" : true,
         "first_name" : "",
         "groups" : [],
         "email" : "etl1p@gmail.com",
         "last_name" : "",
         "user_permissions" : [],
         "password" : "",
         "date_joined" : "2016-10-25T20:12:27.504Z",
         "is_superuser" : false
      }
   },
   {
      "pk" : 20,
      "model" : "auth.user",
      "fields" : {
         "user_permissions" : [],
         "password" : "",
         "date_joined" : "2016-10-25T20:12:27.514Z",
         "is_superuser" : false,
         "groups" : [],
         "email" : "7jl2g@gmail.com",
         "last_name" : "",
         "is_active" : true,
         "first_name" : "",
         "username" : "ewest",
         "last_login" : null,
         "is_staff" : false
      }
   },
   {
      "fields" : {
         "password" : "",
         "date_joined" : "2016-10-25T20:12:27.524Z",
         "user_permissions" : [],
         "is_superuser" : false,
         "last_name" : "",
         "email" : "8df3x@gmail.com",
         "groups" : [],
         "first_name" : "",
         "is_active" : true,
         "username" : "shuelse",
         "is_staff" : false,
         "last_login" : null
      },
      "model" : "auth.user",
      "pk" : 21
   },
   {
      "model" : "auth.user",
      "pk" : 22,
      "fields" : {
         "user_permissions" : [],
         "password" : "",
         "date_joined" : "2016-10-25T20:12:27.534Z",
         "is_superuser" : false,
         "groups" : [],
         "last_name" : "",
         "email" : "r9nj4@gmail.com",
         "is_active" : true,
         "first_name" : "",
         "username" : "lsiwiec",
         "last_login" : null,
         "is_staff" : false
      }
   },
   {
      "pk" : 23,
      "model" : "auth.user",
      "fields" : {
         "first_name" : "",
         "is_active" : true,
         "is_staff" : false,
         "last_login" : null,
         "username" : "cgumbs",
         "is_superuser" : false,
         "password" : "",
         "date_joined" : "2016-10-25T20:12:27.544Z",
         "user_permissions" : [],
         "last_name" : "",
         "email" : "57j0o@gmail.com",
         "groups" : []
      }
   },
   {
      "pk" : 24,
      "model" : "auth.user",
      "fields" : {
         "username" : "jmaldonado",
         "is_staff" : false,
         "last_login" : null,
         "first_name" : "",
         "is_active" : true,
         "email" : "7noc6@gmail.com",
         "last_name" : "",
         "groups" : [],
         "password" : "",
         "date_joined" : "2016-10-25T20:12:27.554Z",
         "user_permissions" : [],
         "is_superuser" : false
      }
   },
   {
      "model" : "auth.user",
      "pk" : 25,
      "fields" : {
         "email" : "ufmio@gmail.com",
         "last_name" : "",
         "groups" : [],
         "password" : "",
         "date_joined" : "2016-10-25T20:12:27.564Z",
         "user_permissions" : [],
         "is_superuser" : false,
         "username" : "psellers",
         "is_staff" : false,
         "last_login" : null,
         "first_name" : "",
         "is_active" : true
      }
   },
   {
      "model" : "auth.user",
      "pk" : 26,
      "fields" : {
         "last_login" : null,
         "is_staff" : false,
         "username" : "pnelson",
         "is_active" : true,
         "first_name" : "",
         "groups" : [],
         "last_name" : "",
         "email" : "efl9g@gmail.com",
         "is_superuser" : false,
         "user_permissions" : [],
         "date_joined" : "2016-10-25T20:12:27.574Z",
         "password" : ""
      }
   },
   {
      "pk" : 27,
      "model" : "auth.user",
      "fields" : {
         "is_active" : true,
         "first_name" : "",
         "last_login" : null,
         "is_staff" : false,
         "username" : "cparsons",
         "is_superuser" : false,
         "user_permissions" : [],
         "password" : "",
         "date_joined" : "2016-10-25T20:12:27.585Z",
         "groups" : [],
         "email" : "kk28a@gmail.com",
         "last_name" : ""
      }
   },
   {
      "pk" : 28,
      "model" : "auth.user",
      "fields" : {
         "first_name" : "",
         "is_active" : true,
         "is_staff" : false,
         "last_login" : null,
         "username" : "jnichols",
         "is_superuser" : false,
         "password" : "",
         "date_joined" : "2016-10-25T20:12:27.595Z",
         "user_permissions" : [],
         "last_name" : "",
         "email" : "s5oqt@gmail.com",
         "groups" : []
      }
   },
   {
      "pk" : 29,
      "model" : "auth.user",
      "fields" : {
         "email" : "67qli@gmail.com",
         "last_name" : "",
         "groups" : [],
         "is_superuser" : false,
         "password" : "",
         "date_joined" : "2016-10-25T20:12:27.604Z",
         "user_permissions" : [],
         "is_staff" : false,
         "last_login" : null,
         "username" : "ntoman",
         "first_name" : "",
         "is_active" : true
      }
   },
   {
      "fields" : {
         "email" : "2wcfq@gmail.com",
         "last_name" : "",
         "groups" : [],
         "is_superuser" : false,
         "date_joined" : "2016-10-25T20:12:27.614Z",
         "password" : "",
         "user_permissions" : [],
         "is_staff" : false,
         "last_login" : null,
         "username" : "alawrence",
         "first_name" : "",
         "is_active" : true
      },
      "model" : "auth.user",
      "pk" : 30
   },
   {
      "fields" : {
         "last_login" : null,
         "is_staff" : false,
         "username" : "rgonzalez",
         "is_active" : true,
         "first_name" : "",
         "groups" : [],
         "last_name" : "",
         "email" : "gt3v9@gmail.com",
         "is_superuser" : false,
         "user_permissions" : [],
         "password" : "",
         "date_joined" : "2016-10-25T20:12:27.623Z"
      },
      "model" : "auth.user",
      "pk" : 31
   },
   {
      "fields" : {
         "is_superuser" : false,
         "password" : "",
         "date_joined" : "2016-10-25T20:12:27.633Z",
         "user_permissions" : [],
         "last_name" : "",
         "email" : "gc40c@gmail.com",
         "groups" : [],
         "first_name" : "",
         "is_active" : true,
         "is_staff" : false,
         "last_login" : null,
         "username" : "sfoote"
      },
      "pk" : 32,
      "model" : "auth.user"
   },
   {
      "fields" : {
         "is_active" : true,
         "first_name" : "",
         "last_login" : null,
         "is_staff" : false,
         "username" : "skwan",
         "is_superuser" : false,
         "user_permissions" : [],
         "date_joined" : "2016-10-25T20:12:27.643Z",
         "password" : "",
         "groups" : [],
         "last_name" : "",
         "email" : "e8zlq@gmail.com"
      },
      "model" : "auth.user",
      "pk" : 33
   },
   {
      "pk" : 34,
      "model" : "auth.user",
      "fields" : {
         "password" : "",
         "date_joined" : "2016-10-25T20:12:27.653Z",
         "user_permissions" : [],
         "is_superuser" : false,
         "email" : "t0pup@gmail.com",
         "last_name" : "",
         "groups" : [],
         "first_name" : "",
         "is_active" : true,
         "username" : "cvonbraunsberg",
         "is_staff" : false,
         "last_login" : null
      }
   },
   {
      "fields" : {
         "is_superuser" : false,
         "date_joined" : "2016-10-25T20:12:27.663Z",
         "password" : "",
         "user_permissions" : [],
         "email" : "s6av1@gmail.com",
         "last_name" : "",
         "groups" : [],
         "first_name" : "",
         "is_active" : true,
         "is_staff" : false,
         "last_login" : null,
         "username" : "ebrown"
      },
      "pk" : 35,
      "model" : "auth.user"
   },
   {
      "pk" : 36,
      "model" : "auth.user",
      "fields" : {
         "is_active" : true,
         "first_name" : "",
         "last_login" : null,
         "is_staff" : false,
         "username" : "fmilosevic",
         "is_superuser" : false,
         "user_permissions" : [],
         "date_joined" : "2016-10-25T20:12:27.674Z",
         "password" : "",
         "groups" : [],
         "last_name" : "",
         "email" : "ul7y5@gmail.com"
      }
   },
   {
      "fields" : {
         "last_login" : null,
         "is_staff" : false,
         "username" : "jlewis",
         "is_active" : true,
         "first_name" : "",
         "groups" : [],
         "last_name" : "",
         "email" : "g998h@gmail.com",
         "is_superuser" : false,
         "user_permissions" : [],
         "date_joined" : "2016-10-25T20:12:27.684Z",
         "password" : ""
      },
      "pk" : 37,
      "model" : "auth.user"
   },
   {
      "fields" : {
         "groups" : [],
         "last_name" : "",
         "email" : "pk2f8@gmail.com",
         "user_permissions" : [],
         "date_joined" : "2016-10-25T20:12:27.694Z",
         "password" : "",
         "is_superuser" : false,
         "username" : "lmedley",
         "last_login" : null,
         "is_staff" : false,
         "is_active" : true,
         "first_name" : ""
      },
      "pk" : 38,
      "model" : "auth.user"
   },
   {
      "fields" : {
         "is_superuser" : false,
         "user_permissions" : [],
         "date_joined" : "2016-10-25T20:12:27.704Z",
         "password" : "",
         "groups" : [],
         "last_name" : "",
         "email" : "3iazc@gmail.com",
         "is_active" : true,
         "first_name" : "",
         "last_login" : null,
         "is_staff" : false,
         "username" : "mkincaid"
      },
      "model" : "auth.user",
      "pk" : 39
   },
   {
      "model" : "auth.user",
      "pk" : 40,
      "fields" : {
         "is_active" : true,
         "first_name" : "",
         "username" : "mcohn",
         "last_login" : null,
         "is_staff" : false,
         "user_permissions" : [],
         "date_joined" : "2016-10-25T20:12:27.714Z",
         "password" : "",
         "is_superuser" : false,
         "groups" : [],
         "email" : "m03as@gmail.com",
         "last_name" : ""
      }
   },
   {
      "model" : "auth.user",
      "pk" : 41,
      "fields" : {
         "is_staff" : false,
         "last_login" : null,
         "username" : "deverts",
         "first_name" : "",
         "is_active" : true,
         "last_name" : "",
         "email" : "ivvlc@gmail.com",
         "groups" : [],
         "is_superuser" : false,
         "password" : "",
         "date_joined" : "2016-10-25T20:12:27.727Z",
         "user_permissions" : []
      }
   },
   {
      "model" : "auth.user",
      "pk" : 42,
      "fields" : {
         "user_permissions" : [],
         "date_joined" : "2016-10-25T20:12:27.738Z",
         "password" : "",
         "is_superuser" : false,
         "groups" : [],
         "email" : "s9qr9@gmail.com",
         "last_name" : "",
         "is_active" : true,
         "first_name" : "",
         "username" : "tlee",
         "last_login" : null,
         "is_staff" : false
      }
   },
   {
      "fields" : {
         "last_login" : null,
         "is_staff" : false,
         "username" : "msykes",
         "is_active" : true,
         "first_name" : "",
         "groups" : [],
         "last_name" : "",
         "email" : "uz36m@gmail.com",
         "is_superuser" : false,
         "user_permissions" : [],
         "password" : "",
         "date_joined" : "2016-10-25T20:12:27.749Z"
      },
      "model" : "auth.user",
      "pk" : 43
   },
   {
      "fields" : {
         "last_login" : null,
         "is_staff" : false,
         "username" : "aharper",
         "is_active" : true,
         "first_name" : "",
         "groups" : [],
         "last_name" : "",
         "email" : "5e1tw@gmail.com",
         "is_superuser" : false,
         "user_permissions" : [],
         "date_joined" : "2016-10-25T20:12:27.759Z",
         "password" : ""
      },
      "pk" : 44,
      "model" : "auth.user"
   },
   {
      "model" : "auth.user",
      "pk" : 45,
      "fields" : {
         "is_superuser" : false,
         "user_permissions" : [],
         "date_joined" : "2016-10-25T20:12:27.770Z",
         "password" : "",
         "groups" : [],
         "email" : "4mj8h@gmail.com",
         "last_name" : "",
         "is_active" : true,
         "first_name" : "",
         "last_login" : null,
         "is_staff" : false,
         "username" : "vhodges"
      }
   },
   {
      "fields" : {
         "groups" : [],
         "last_name" : "",
         "email" : "7q3og@gmail.com",
         "user_permissions" : [],
         "date_joined" : "2016-10-25T20:12:27.779Z",
         "password" : "",
         "is_superuser" : false,
         "username" : "lguardipee",
         "last_login" : null,
         "is_staff" : false,
         "is_active" : true,
         "first_name" : ""
      },
      "pk" : 46,
      "model" : "auth.user"
   },
   {
      "pk" : 47,
      "model" : "auth.user",
      "fields" : {
         "is_active" : true,
         "first_name" : "",
         "last_login" : null,
         "is_staff" : false,
         "username" : "dmacdonald",
         "is_superuser" : false,
         "user_permissions" : [],
         "password" : "",
         "date_joined" : "2016-10-25T20:12:27.790Z",
         "groups" : [],
         "last_name" : "",
         "email" : "76nwj@gmail.com"
      }
   },
   {
      "model" : "auth.user",
      "pk" : 48,
      "fields" : {
         "last_name" : "",
         "email" : "s8cuw@gmail.com",
         "groups" : [],
         "is_superuser" : false,
         "password" : "",
         "date_joined" : "2016-10-25T20:12:27.800Z",
         "user_permissions" : [],
         "is_staff" : false,
         "last_login" : null,
         "username" : "pgoodson",
         "first_name" : "",
         "is_active" : true
      }
   },
   {
      "fields" : {
         "date_joined" : "2016-10-25T20:12:27.810Z",
         "password" : "",
         "user_permissions" : [],
         "is_superuser" : false,
         "email" : "5ejkm@gmail.com",
         "last_name" : "",
         "groups" : [],
         "first_name" : "",
         "is_active" : true,
         "username" : "lbetterton",
         "is_staff" : false,
         "last_login" : null
      },
      "model" : "auth.user",
      "pk" : 49
   },
   {
      "pk" : 50,
      "model" : "auth.user",
      "fields" : {
         "last_login" : null,
         "is_staff" : false,
         "username" : "sgaddis",
         "is_active" : true,
         "first_name" : "",
         "groups" : [],
         "last_name" : "",
         "email" : "8jmy5@gmail.com",
         "is_superuser" : false,
         "user_permissions" : [],
         "date_joined" : "2016-10-25T20:12:27.823Z",
         "password" : ""
      }
   },
   {
      "fields" : {
         "is_staff" : false,
         "last_login" : null,
         "username" : "jmcgill",
         "first_name" : "",
         "is_active" : true,
         "last_name" : "",
         "email" : "f9yby@gmail.com",
         "groups" : [],
         "is_superuser" : false,
         "password" : "",
         "date_joined" : "2016-10-25T20:12:27.833Z",
         "user_permissions" : []
      },
      "model" : "auth.user",
      "pk" : 51
   },
   {
      "fields" : {
         "is_staff" : false,
         "last_login" : null,
         "username" : "kbaxter",
         "first_name" : "",
         "is_active" : true,
         "email" : "7ljmv@gmail.com",
         "last_name" : "",
         "groups" : [],
         "is_superuser" : false,
         "password" : "",
         "date_joined" : "2016-10-25T20:12:27.842Z",
         "user_permissions" : []
      },
      "pk" : 52,
      "model" : "auth.user"
   },
   {
      "pk" : 53,
      "model" : "auth.user",
      "fields" : {
         "last_login" : null,
         "is_staff" : false,
         "username" : "aschultz",
         "is_active" : true,
         "first_name" : "",
         "groups" : [],
         "email" : "pt5nu@gmail.com",
         "last_name" : "",
         "is_superuser" : false,
         "user_permissions" : [],
         "date_joined" : "2016-10-25T20:12:27.852Z",
         "password" : ""
      }
   },
   {
      "fields" : {
         "username" : "dhorrigan",
         "last_login" : null,
         "is_staff" : false,
         "is_active" : true,
         "first_name" : "",
         "groups" : [],
         "last_name" : "",
         "email" : "ia11x@gmail.com",
         "user_permissions" : [],
         "date_joined" : "2016-10-25T20:12:27.866Z",
         "password" : "",
         "is_superuser" : false
      },
      "pk" : 54,
      "model" : "auth.user"
   },
   {
      "fields" : {
         "username" : "lsanchez",
         "last_login" : null,
         "is_staff" : false,
         "is_active" : true,
         "first_name" : "",
         "groups" : [],
         "email" : "q5mo0@gmail.com",
         "last_name" : "",
         "user_permissions" : [],
         "date_joined" : "2016-10-25T20:12:27.877Z",
         "password" : "",
         "is_superuser" : false
      },
      "model" : "auth.user",
      "pk" : 55
   },
   {
      "model" : "auth.user",
      "pk" : 56,
      "fields" : {
         "is_active" : true,
         "first_name" : "",
         "username" : "alaborde",
         "last_login" : null,
         "is_staff" : false,
         "user_permissions" : [],
         "password" : "",
         "date_joined" : "2016-10-25T20:12:27.888Z",
         "is_superuser" : false,
         "groups" : [],
         "email" : "kwfzl@gmail.com",
         "last_name" : ""
      }
   },
   {
      "fields" : {
         "is_superuser" : false,
         "user_permissions" : [],
         "password" : "",
         "date_joined" : "2016-10-25T20:12:27.898Z",
         "groups" : [],
         "last_name" : "",
         "email" : "tykrg@gmail.com",
         "is_active" : true,
         "first_name" : "",
         "last_login" : null,
         "is_staff" : false,
         "username" : "dharkins"
      },
      "pk" : 57,
      "model" : "auth.user"
   },
   {
      "fields" : {
         "is_staff" : false,
         "last_login" : null,
         "username" : "wgualtieri",
         "first_name" : "",
         "is_active" : true,
         "email" : "ohxnh@gmail.com",
         "last_name" : "",
         "groups" : [],
         "is_superuser" : false,
         "password" : "",
         "date_joined" : "2016-10-25T20:12:27.908Z",
         "user_permissions" : []
      },
      "model" : "auth.user",
      "pk" : 58
   },
   {
      "fields" : {
         "is_active" : true,
         "first_name" : "",
         "last_login" : null,
         "is_staff" : false,
         "username" : "phuslander",
         "is_superuser" : false,
         "user_permissions" : [],
         "date_joined" : "2016-10-25T20:12:27.919Z",
         "password" : "",
         "groups" : [],
         "last_name" : "",
         "email" : "myg04@gmail.com"
      },
      "pk" : 59,
      "model" : "auth.user"
   },
   {
      "model" : "auth.user",
      "pk" : 60,
      "fields" : {
         "email" : "7h8yd@gmail.com",
         "last_name" : "",
         "groups" : [],
         "is_superuser" : false,
         "date_joined" : "2016-10-25T20:12:27.929Z",
         "password" : "",
         "user_permissions" : [],
         "is_staff" : false,
         "last_login" : null,
         "username" : "cwilson",
         "first_name" : "",
         "is_active" : true
      }
   },
   {
      "model" : "auth.user",
      "pk" : 61,
      "fields" : {
         "username" : "hphillips",
         "is_staff" : false,
         "last_login" : null,
         "first_name" : "",
         "is_active" : true,
         "last_name" : "",
         "email" : "d035v@gmail.com",
         "groups" : [],
         "date_joined" : "2016-10-25T20:12:27.939Z",
         "password" : "",
         "user_permissions" : [],
         "is_superuser" : false
      }
   },
   {
      "fields" : {
         "is_active" : true,
         "first_name" : "",
         "last_login" : null,
         "is_staff" : false,
         "username" : "emcdonald",
         "is_superuser" : false,
         "user_permissions" : [],
         "date_joined" : "2016-10-25T20:12:27.949Z",
         "password" : "",
         "groups" : [],
         "last_name" : "",
         "email" : "po5xp@gmail.com"
      },
      "pk" : 62,
      "model" : "auth.user"
   },
   {
      "fields" : {
         "first_name" : "",
         "is_active" : true,
         "is_staff" : false,
         "last_login" : null,
         "username" : "rhudson",
         "is_superuser" : false,
         "date_joined" : "2016-10-25T20:12:27.959Z",
         "password" : "",
         "user_permissions" : [],
         "last_name" : "",
         "email" : "d2u1c@gmail.com",
         "groups" : []
      },
      "model" : "auth.user",
      "pk" : 63
   },
   {
      "pk" : 64,
      "model" : "auth.user",
      "fields" : {
         "last_name" : "",
         "email" : "5qdvm@gmail.com",
         "groups" : [],
         "date_joined" : "2016-10-25T20:12:27.969Z",
         "password" : "",
         "user_permissions" : [],
         "is_superuser" : false,
         "username" : "jmcneill",
         "is_staff" : false,
         "last_login" : null,
         "first_name" : "",
         "is_active" : true
      }
   },
   {
      "model" : "auth.user",
      "pk" : 65,
      "fields" : {
         "is_active" : true,
         "first_name" : "",
         "username" : "jfrancis",
         "last_login" : null,
         "is_staff" : false,
         "user_permissions" : [],
         "date_joined" : "2016-10-25T20:12:27.980Z",
         "password" : "",
         "is_superuser" : false,
         "groups" : [],
         "email" : "m6cr9@gmail.com",
         "last_name" : ""
      }
   },
   {
      "fields" : {
         "groups" : [],
         "last_name" : "",
         "email" : "7adh9@gmail.com",
         "user_permissions" : [],
         "password" : "",
         "date_joined" : "2016-10-25T20:12:27.990Z",
         "is_superuser" : false,
         "username" : "mbest",
         "last_login" : null,
         "is_staff" : false,
         "is_active" : true,
         "first_name" : ""
      },
      "model" : "auth.user",
      "pk" : 66
   },
   {
      "fields" : {
         "is_staff" : false,
         "last_login" : null,
         "username" : "etaylor",
         "first_name" : "",
         "is_active" : true,
         "last_name" : "",
         "email" : "95i7z@gmail.com",
         "groups" : [],
         "is_superuser" : false,
         "date_joined" : "2016-10-25T20:12:28Z",
         "password" : "",
         "user_permissions" : []
      },
      "model" : "auth.user",
      "pk" : 67
   },
   {
      "fields" : {
         "groups" : [],
         "email" : "kkcns@gmail.com",
         "last_name" : "",
         "is_superuser" : false,
         "user_permissions" : [],
         "password" : "",
         "date_joined" : "2016-10-25T20:12:28.010Z",
         "last_login" : null,
         "is_staff" : false,
         "username" : "hrobinson",
         "is_active" : true,
         "first_name" : ""
      },
      "pk" : 68,
      "model" : "auth.user"
   },
   {
      "fields" : {
         "username" : "tirwin",
         "is_staff" : false,
         "last_login" : null,
         "first_name" : "",
         "is_active" : true,
         "last_name" : "",
         "email" : "ddvsw@gmail.com",
         "groups" : [],
         "password" : "",
         "date_joined" : "2016-10-25T20:12:28.020Z",
         "user_permissions" : [],
         "is_superuser" : false
      },
      "pk" : 69,
      "model" : "auth.user"
   },
   {
      "pk" : 70,
      "model" : "auth.user",
      "fields" : {
         "user_permissions" : [],
         "password" : "",
         "date_joined" : "2016-10-25T20:12:28.030Z",
         "is_superuser" : false,
         "groups" : [],
         "last_name" : "",
         "email" : "8vrsm@gmail.com",
         "is_active" : true,
         "first_name" : "",
         "username" : "lleffew",
         "last_login" : null,
         "is_staff" : false
      }
   },
   {
      "model" : "auth.user",
      "pk" : 71,
      "fields" : {
         "last_name" : "",
         "email" : "omc0m@gmail.com",
         "groups" : [],
         "date_joined" : "2016-10-25T20:12:28.040Z",
         "password" : "",
         "user_permissions" : [],
         "is_superuser" : false,
         "username" : "kparker",
         "is_staff" : false,
         "last_login" : null,
         "first_name" : "",
         "is_active" : true
      }
   },
   {
      "pk" : 72,
      "model" : "auth.user",
      "fields" : {
         "username" : "lvancleave",
         "is_staff" : false,
         "last_login" : null,
         "first_name" : "",
         "is_active" : true,
         "email" : "i8y3p@gmail.com",
         "last_name" : "",
         "groups" : [],
         "password" : "",
         "date_joined" : "2016-10-25T20:12:28.050Z",
         "user_permissions" : [],
         "is_superuser" : false
      }
   },
   {
      "model" : "auth.user",
      "pk" : 73,
      "fields" : {
         "groups" : [],
         "email" : "ghnrz@gmail.com",
         "last_name" : "",
         "is_superuser" : false,
         "user_permissions" : [],
         "date_joined" : "2016-10-25T20:12:28.060Z",
         "password" : "",
         "last_login" : null,
         "is_staff" : false,
         "username" : "mlandi",
         "is_active" : true,
         "first_name" : ""
      }
   },
   {
      "model" : "auth.user",
      "pk" : 74,
      "fields" : {
         "groups" : [],
         "last_name" : "",
         "email" : "06g2m@gmail.com",
         "is_superuser" : false,
         "user_permissions" : [],
         "password" : "",
         "date_joined" : "2016-10-25T20:12:28.070Z",
         "last_login" : null,
         "is_staff" : false,
         "username" : "lkesler",
         "is_active" : true,
         "first_name" : ""
      }
   },
   {
      "fields" : {
         "is_superuser" : false,
         "date_joined" : "2016-10-25T20:12:28.080Z",
         "password" : "",
         "user_permissions" : [],
         "email" : "lx9p9@gmail.com",
         "last_name" : "",
         "groups" : [],
         "first_name" : "",
         "is_active" : true,
         "is_staff" : false,
         "last_login" : null,
         "username" : "drice"
      },
      "model" : "auth.user",
      "pk" : 75
   },
   {
      "pk" : 76,
      "model" : "auth.user",
      "fields" : {
         "groups" : [],
         "last_name" : "",
         "email" : "exhlc@gmail.com",
         "is_superuser" : false,
         "user_permissions" : [],
         "date_joined" : "2016-10-25T20:12:28.090Z",
         "password" : "",
         "last_login" : null,
         "is_staff" : false,
         "username" : "msalido",
         "is_active" : true,
         "first_name" : ""
      }
   },
   {
      "model" : "auth.user",
      "pk" : 77,
      "fields" : {
         "groups" : [],
         "last_name" : "",
         "email" : "13kqa@gmail.com",
         "user_permissions" : [],
         "date_joined" : "2016-10-25T20:12:28.100Z",
         "password" : "",
         "is_superuser" : false,
         "username" : "mmcdowell",
         "last_login" : null,
         "is_staff" : false,
         "is_active" : true,
         "first_name" : ""
      }
   },
   {
      "fields" : {
         "username" : "vbowley",
         "last_login" : null,
         "is_staff" : false,
         "is_active" : true,
         "first_name" : "",
         "groups" : [],
         "email" : "xayem@gmail.com",
         "last_name" : "",
         "user_permissions" : [],
         "date_joined" : "2016-10-25T20:12:28.114Z",
         "password" : "",
         "is_superuser" : false
      },
      "model" : "auth.user",
      "pk" : 78
   },
   {
      "fields" : {
         "is_active" : true,
         "first_name" : "",
         "last_login" : null,
         "is_staff" : false,
         "username" : "cbrown",
         "is_superuser" : false,
         "user_permissions" : [],
         "password" : "",
         "date_joined" : "2016-10-25T20:12:28.124Z",
         "groups" : [],
         "email" : "uh57d@gmail.com",
         "last_name" : ""
      },
      "pk" : 79,
      "model" : "auth.user"
   },
   {
      "fields" : {
         "first_name" : "",
         "is_active" : true,
         "username" : "frhoades",
         "is_staff" : false,
         "last_login" : null,
         "date_joined" : "2016-10-25T20:12:28.133Z",
         "password" : "",
         "user_permissions" : [],
         "is_superuser" : false,
         "email" : "kwydc@gmail.com",
         "last_name" : "",
         "groups" : []
      },
      "pk" : 80,
      "model" : "auth.user"
   },
   {
      "fields" : {
         "groups" : [],
         "email" : "nk9an@gmail.com",
         "last_name" : "",
         "user_permissions" : [],
         "password" : "",
         "date_joined" : "2016-10-25T20:12:28.142Z",
         "is_superuser" : false,
         "username" : "emyers",
         "last_login" : null,
         "is_staff" : false,
         "is_active" : true,
         "first_name" : ""
      },
      "pk" : 81,
      "model" : "auth.user"
   },
   {
      "fields" : {
         "is_active" : true,
         "first_name" : "",
         "last_login" : null,
         "is_staff" : false,
         "username" : "rdavid",
         "is_superuser" : false,
         "user_permissions" : [],
         "date_joined" : "2016-10-25T20:12:28.151Z",
         "password" : "",
         "groups" : [],
         "email" : "zl3h2@gmail.com",
         "last_name" : ""
      },
      "model" : "auth.user",
      "pk" : 82
   },
   {
      "fields" : {
         "groups" : [],
         "last_name" : "",
         "email" : "vbu81@gmail.com",
         "is_superuser" : false,
         "user_permissions" : [],
         "date_joined" : "2016-10-25T20:12:28.162Z",
         "password" : "",
         "last_login" : null,
         "is_staff" : false,
         "username" : "mhelms",
         "is_active" : true,
         "first_name" : ""
      },
      "model" : "auth.user",
      "pk" : 83
   },
   {
      "fields" : {
         "groups" : [],
         "last_name" : "",
         "email" : "5z1a8@gmail.com",
         "is_superuser" : false,
         "user_permissions" : [],
         "date_joined" : "2016-10-25T20:12:28.172Z",
         "password" : "",
         "last_login" : null,
         "is_staff" : false,
         "username" : "zroe",
         "is_active" : true,
         "first_name" : ""
      },
      "pk" : 84,
      "model" : "auth.user"
   },
   {
      "fields" : {
         "first_name" : "",
         "is_active" : true,
         "is_staff" : false,
         "last_login" : null,
         "username" : "jlillis",
         "is_superuser" : false,
         "date_joined" : "2016-10-25T20:12:28.182Z",
         "password" : "",
         "user_permissions" : [],
         "email" : "xbg1u@gmail.com",
         "last_name" : "",
         "groups" : []
      },
      "pk" : 85,
      "model" : "auth.user"
   },
   {
      "model" : "auth.user",
      "pk" : 86,
      "fields" : {
         "is_active" : true,
         "first_name" : "",
         "username" : "lgonzalez",
         "last_login" : null,
         "is_staff" : false,
         "user_permissions" : [],
         "date_joined" : "2016-10-25T20:12:28.193Z",
         "password" : "",
         "is_superuser" : false,
         "groups" : [],
         "email" : "f28rl@gmail.com",
         "last_name" : ""
      }
   },
   {
      "fields" : {
         "last_name" : "",
         "email" : "oala1@gmail.com",
         "groups" : [],
         "is_superuser" : false,
         "date_joined" : "2016-10-25T20:12:28.203Z",
         "password" : "",
         "user_permissions" : [],
         "is_staff" : false,
         "last_login" : null,
         "username" : "mswitzer",
         "first_name" : "",
         "is_active" : true
      },
      "model" : "auth.user",
      "pk" : 87
   },
   {
      "model" : "auth.user",
      "pk" : 88,
      "fields" : {
         "username" : "dmoffat",
         "last_login" : null,
         "is_staff" : false,
         "is_active" : true,
         "first_name" : "",
         "groups" : [],
         "email" : "0gz7x@gmail.com",
         "last_name" : "",
         "user_permissions" : [],
         "password" : "",
         "date_joined" : "2016-10-25T20:12:28.213Z",
         "is_superuser" : false
      }
   },
   {
      "model" : "auth.user",
      "pk" : 89,
      "fields" : {
         "last_name" : "",
         "email" : "q0z4g@gmail.com",
         "groups" : [],
         "is_superuser" : false,
         "password" : "",
         "date_joined" : "2016-10-25T20:12:28.227Z",
         "user_permissions" : [],
         "is_staff" : false,
         "last_login" : null,
         "username" : "lfields",
         "first_name" : "",
         "is_active" : true
      }
   },
   {
      "fields" : {
         "user_permissions" : [],
         "password" : "",
         "date_joined" : "2016-10-25T20:12:28.237Z",
         "is_superuser" : false,
         "groups" : [],
         "last_name" : "",
         "email" : "jmtwz@gmail.com",
         "is_active" : true,
         "first_name" : "",
         "username" : "nhallack",
         "last_login" : null,
         "is_staff" : false
      },
      "pk" : 90,
      "model" : "auth.user"
   },
   {
      "pk" : 91,
      "model" : "auth.user",
      "fields" : {
         "last_login" : null,
         "is_staff" : false,
         "username" : "cmyers",
         "is_active" : true,
         "first_name" : "",
         "groups" : [],
         "last_name" : "",
         "email" : "qk8ho@gmail.com",
         "is_superuser" : false,
         "user_permissions" : [],
         "password" : "",
         "date_joined" : "2016-10-25T20:12:28.247Z"
      }
   },
   {
      "pk" : 92,
      "model" : "auth.user",
      "fields" : {
         "username" : "mkeri",
         "is_staff" : false,
         "last_login" : null,
         "first_name" : "",
         "is_active" : true,
         "email" : "6x0on@gmail.com",
         "last_name" : "",
         "groups" : [],
         "password" : "",
         "date_joined" : "2016-10-25T20:12:28.257Z",
         "user_permissions" : [],
         "is_superuser" : false
      }
   },
   {
      "pk" : 93,
      "model" : "auth.user",
      "fields" : {
         "is_active" : true,
         "first_name" : "",
         "last_login" : null,
         "is_staff" : false,
         "username" : "nhartley",
         "is_superuser" : false,
         "user_permissions" : [],
         "date_joined" : "2016-10-25T20:12:28.267Z",
         "password" : "",
         "groups" : [],
         "email" : "9z25b@gmail.com",
         "last_name" : ""
      }
   },
   {
      "fields" : {
         "username" : "spettis",
         "is_staff" : false,
         "last_login" : null,
         "first_name" : "",
         "is_active" : true,
         "last_name" : "",
         "email" : "dbhjl@gmail.com",
         "groups" : [],
         "password" : "",
         "date_joined" : "2016-10-25T20:12:28.277Z",
         "user_permissions" : [],
         "is_superuser" : false
      },
      "pk" : 94,
      "model" : "auth.user"
   },
   {
      "fields" : {
         "is_superuser" : false,
         "password" : "",
         "date_joined" : "2016-10-25T20:12:28.288Z",
         "user_permissions" : [],
         "email" : "e834l@gmail.com",
         "last_name" : "",
         "groups" : [],
         "first_name" : "",
         "is_active" : true,
         "is_staff" : false,
         "last_login" : null,
         "username" : "clastrapes"
      },
      "pk" : 95,
      "model" : "auth.user"
   },
   {
      "model" : "auth.user",
      "pk" : 96,
      "fields" : {
         "username" : "lcolantuono",
         "last_login" : null,
         "is_staff" : false,
         "is_active" : true,
         "first_name" : "",
         "groups" : [],
         "email" : "ovq5q@gmail.com",
         "last_name" : "",
         "user_permissions" : [],
         "password" : "",
         "date_joined" : "2016-10-25T20:12:28.297Z",
         "is_superuser" : false
      }
   },
   {
      "pk" : 97,
      "model" : "auth.user",
      "fields" : {
         "email" : "n1moe@gmail.com",
         "last_name" : "",
         "groups" : [],
         "is_superuser" : false,
         "date_joined" : "2016-10-25T20:12:28.308Z",
         "password" : "",
         "user_permissions" : [],
         "is_staff" : false,
         "last_login" : null,
         "username" : "kmiller",
         "first_name" : "",
         "is_active" : true
      }
   },
   {
      "fields" : {
         "first_name" : "",
         "is_active" : true,
         "is_staff" : false,
         "last_login" : null,
         "username" : "nsantiago",
         "is_superuser" : false,
         "date_joined" : "2016-10-25T20:12:28.321Z",
         "password" : "",
         "user_permissions" : [],
         "last_name" : "",
         "email" : "1jlo9@gmail.com",
         "groups" : []
      },
      "pk" : 98,
      "model" : "auth.user"
   },
   {
      "pk" : 99,
      "model" : "auth.user",
      "fields" : {
         "date_joined" : "2016-10-25T20:12:28.331Z",
         "password" : "",
         "user_permissions" : [],
         "is_superuser" : false,
         "last_name" : "",
         "email" : "h9md7@gmail.com",
         "groups" : [],
         "first_name" : "",
         "is_active" : true,
         "username" : "sburgess",
         "is_staff" : false,
         "last_login" : null
      }
   },
   {
      "model" : "auth.user",
      "pk" : 100,
      "fields" : {
         "email" : "m1l2q@gmail.com",
         "last_name" : "",
         "groups" : [],
         "password" : "",
         "date_joined" : "2016-10-25T20:12:28.342Z",
         "user_permissions" : [],
         "is_superuser" : false,
         "username" : "bguyer",
         "is_staff" : false,
         "last_login" : null,
         "first_name" : "",
         "is_active" : true
      }
   },
   {
      "fields" : {
         "date_joined" : "2016-10-25T20:12:28.352Z",
         "password" : "",
         "user_permissions" : [],
         "is_superuser" : false,
         "last_name" : "",
         "email" : "z3iss@gmail.com",
         "groups" : [],
         "first_name" : "",
         "is_active" : true,
         "username" : "egouty",
         "is_staff" : false,
         "last_login" : null
      },
      "model" : "auth.user",
      "pk" : 101
   }
]
